httpie_snapdsocket.py
httpie_snapdsocket-1.0.0.dist-info/LICENSE
httpie_snapdsocket-1.0.0.dist-info/METADATA
httpie_snapdsocket-1.0.0.dist-info/WHEEL
httpie_snapdsocket-1.0.0.dist-info/entry_points.txt
httpie_snapdsocket-1.0.0.dist-info/top_level.txt
httpie_snapdsocket-1.0.0.dist-info/RECORD
