Metadata-Version: 2.1
Name: httpie-snapdsocket
Version: 1.0.0
Summary: Snapd socket transport plugin for HTTPie.
Home-page: https://github.com/httpie/httpie-snapdsocket
Author: Mickaël Schoentgen
Author-email: mickael@apible.io
License: BSD
Platform: UNKNOWN
Classifier: Development Status :: 5 - Production/Stable
Classifier: Programming Language :: Python
Classifier: Programming Language :: Python :: 3
Classifier: Programming Language :: Python :: 3.6
Classifier: Programming Language :: Python :: 3.7
Classifier: Programming Language :: Python :: 3.8
Classifier: Programming Language :: Python :: 3.9
Classifier: Programming Language :: Python :: 3.10
Classifier: Environment :: Plugins
Classifier: License :: OSI Approved :: BSD License
Classifier: Topic :: Internet :: WWW/HTTP
Classifier: Topic :: Utilities
License-File: LICENSE
Requires-Dist: httpie
Requires-Dist: requests-unixsocket
